implicits/__init__.py
implicits-1.0.2.dist-info/METADATA
implicits-1.0.2.dist-info/RECORD
implicits-1.0.2.dist-info/WHEEL
implicits-1.0.2.dist-info/top_level.txt
implicits-1.0.2.dist-info/zip-safe
