Metadata-Version: 1.1
Name: implicits
Version: 1.0.2
Summary: Implicit parameters in Python
Home-page: https://github.com/JadenGeller/Implicits
Author: Jaden Geller
Author-email: UNKNOWN
License: MIT
Keywords: implicit implicits arguments parameters scala context locals
Platform: UNKNOWN
Classifier: Intended Audience :: Developers
Classifier: Intended Audience :: Education
Classifier: Topic :: Software Development :: Libraries
Classifier: License :: OSI Approved :: MIT License
Classifier: Programming Language :: Python
